IJython/__init__.py
IJython/jython_kernel.py
jython_kernel-2.0.dist-info/DESCRIPTION.rst
jython_kernel-2.0.dist-info/METADATA
jython_kernel-2.0.dist-info/RECORD
jython_kernel-2.0.dist-info/WHEEL
jython_kernel-2.0.dist-info/metadata.json
jython_kernel-2.0.dist-info/top_level.txt
