Metadata-Version: 2.0
Name: jython-kernel
Version: 2.0
Summary: A Jython kernel for Jupyter/IPython
Home-page: https://github.com/suvarchal/IJython
Author: Suvarchal Kumar Cheedela
Author-email: suvarchal.kumar@gmail.com
License: MIT
Platform: UNKNOWN
Classifier: Framework :: IPython
Classifier: License :: OSI Approved :: BSD License
Classifier: Programming Language :: Python :: 2
Classifier: Topic :: System :: Shells
Requires-Dist: IPython (>=3.0)
Requires-Dist: jupyter-client
